pyznuny/__init__.py
pyznuny/ticket/__init__.py
pyznuny/ticket/client.py
pyznuny/ticket/endpoints.py
pyznuny/ticket/exceptions.py
pyznuny/ticket/models.py
pyznuny/ticket/routes.py
pyznuny-0.0.8.dist-info/licenses/LICENSE
pyznuny-0.0.8.dist-info/METADATA
pyznuny-0.0.8.dist-info/WHEEL
pyznuny-0.0.8.dist-info/top_level.txt
pyznuny-0.0.8.dist-info/RECORD
