Metadata-Version: 2.4
Name: pyznuny
Version: 0.0.8
Summary: A Python client for interacting with the Znuny ticketing system API.
Author-email: Junior Rosa <jr.dasrosas@gmail.com>, Pablo Gascon <pablogasconiel445@gmail.com>
Project-URL: Homepage, https://github.com/Junior-Rosa/py-znuny
Project-URL: Repository, https://github.com/Junior-Rosa/py-znuny
Project-URL: Issues, https://github.com/Junior-Rosa/py-znuny/issues
Project-URL: Documentation, https://pyznuny.readthedocs.io/en/latest/
Classifier: Development Status :: 3 - Alpha
Classifier: Intended Audience :: Developers
Classifier: Operating System :: OS Independent
Classifier: Programming Language :: Python
Classifier: Programming Language :: Python :: 3
Classifier: Programming Language :: Python :: 3 :: Only
Classifier: Programming Language :: Python :: 3.10
Classifier: Programming Language :: Python :: 3.11
Classifier: Programming Language :: Python :: 3.12
Classifier: Programming Language :: Python :: 3.13
Classifier: Typing :: Typed
Requires-Python: >=3.10
License-File: LICENSE
Requires-Dist: httpx>=0.28.1
Requires-Dist: pydantic>=2.12.5
Dynamic: license-file
